LICENSE
MANIFEST.in
README.rst
requirements.txt
requirements_for_test.txt
setup.py
istat/__init__.py
istat/istat_area.py
istat/istat_dataset.py
istat/istat_dimension.py
istat/istat_exception.py
istat/istat_functions.py
istat/istat_helper.py
istat/istat_root.py
istat/options.py
jsonstat/__init__.py
jsonstat/collection.py
jsonstat/dataset.py
jsonstat/dimension.py
jsonstat/downloader.py
jsonstat/exceptions.py
jsonstat/parse_functions.py
jsonstat/schema.py
jsonstat/utility.py
jsonstat/value.py
jsonstat/version.py
jsonstat.py.egg-info/PKG-INFO
jsonstat.py.egg-info/SOURCES.txt
jsonstat.py.egg-info/dependency_links.txt
jsonstat.py.egg-info/entry_points.txt
jsonstat.py.egg-info/requires.txt
jsonstat.py.egg-info/top_level.txt
jsonstat/cli/__init__.py
jsonstat/cli/cli_jsonstat.py