Metadata-Version: 1.1
Name: jsonstat.py
Version: 0.1.11
Summary: Library for reading JSON-stat format data.
Home-page: https://github.com/26fe/jsonstat.py
Author: 26fe
Author-email: gf@26fe.com
License: LGPL
Keywords: jsonstat jsonstats json statistics
Platform: UNKNOWN
Classifier: Development Status :: 4 - Beta
Classifier: Intended Audience :: Developers
Classifier: Topic :: Software Development :: Libraries
Classifier: Topic :: Software Development :: Libraries :: Python Modules
Classifier: Environment :: Console
Classifier: License :: OSI Approved :: GNU Lesser General Public License v3 (LGPLv3)
Classifier: Programming Language :: Python :: 2.7
Classifier: Programming Language :: Python :: 3.5
